LICENSE
MANIFEST.in
README.md
setup.cfg
setup.py
pythales/__init__.py
pythales/hsm.py
pythales/tests.py
pythales.egg-info/PKG-INFO
pythales.egg-info/SOURCES.txt
pythales.egg-info/dependency_links.txt
pythales.egg-info/requires.txt
pythales.egg-info/top_level.txt
pythales.egg-info/zip-safe