Metadata-Version: 1.1
Name: pythales
Version: 0.74
Summary: python thales hsm simulator
Home-page: https://github.com/timgabets/pythales
Author: Tim Gabets
Author-email: tim@gabets.ru
License: LGPLv2
Keywords: thales hsm
Platform: UNKNOWN
Classifier: License :: OSI Approved :: GNU Lesser General Public License v2 (LGPLv2)
Classifier: Operating System :: OS Independent
Classifier: Programming Language :: Python :: 3
Classifier: Programming Language :: Python :: 3.3
Classifier: Programming Language :: Python :: 3.4
Classifier: Programming Language :: Python :: 3.5
Classifier: Topic :: Communications
Classifier: Intended Audience :: Developers
